classfig.py
classfig-0.3.2.dist-info/LICENSE
classfig-0.3.2.dist-info/METADATA
classfig-0.3.2.dist-info/WHEEL
classfig-0.3.2.dist-info/RECORD
